{"cameraMode":{"drawMode":0,"name":"Shaded","section":"Shading Mode"},"sceneLighting":true,"audioPlay":false,"sceneViewState":{"m_AlwaysRefresh":false,"showFog":true,"showSkybox":true,"showFlares":true,"showImageEffects":true,"showParticleSystems":true,"showVisualEffectGraphs":true,"m_FxEnabled":true},"in2DMode":false,"pivot":{"x":663.411376953125,"y":20.93077850341797,"z":503.76971435546877},"rotation":{"x":-0.22162851691246034,"y":-0.454928457736969,"z":0.11812480539083481,"w":-0.854621171951294},"size":10.0,"orthographic":false}